event_notifier/__init__.py
event_notifier/notifier.py
event_sms_notifier-0.1.0.dist-info/LICENSE
event_sms_notifier-0.1.0.dist-info/METADATA
event_sms_notifier-0.1.0.dist-info/WHEEL
event_sms_notifier-0.1.0.dist-info/top_level.txt
event_sms_notifier-0.1.0.dist-info/RECORD
