Metadata-Version: 2.1
Name: event-sms-notifier
Version: 0.1.0
Summary: A library for event notifications with SMS capabilities using Africa's Talking
Author:  Namugga Sharifah
Author-email: sharifahnamugga3@gmail.com
Keywords: event notification sms africa's talking period tracking reminder
Classifier: Development Status :: 3 - Alpha
Classifier: Intended Audience :: Developers
Classifier: Topic :: Software Development :: Libraries :: Python Modules
Classifier: License :: OSI Approved :: MIT License
Classifier: Programming Language :: Python :: 3
Classifier: Programming Language :: Python :: 3.6
Classifier: Programming Language :: Python :: 3.7
Classifier: Programming Language :: Python :: 3.8
Classifier: Programming Language :: Python :: 3.9
Classifier: Programming Language :: Python :: 3.10
Classifier: Operating System :: OS Independent
Requires-Python: >=3.6
License-File: LICENSE
Requires-Dist: africastalking>=1.2.5
Requires-Dist: requests>=2.28.0
